mcp_framework/__init__.py
mcp_framework/build.py
mcp_framework/cli.py
mcp_framework/optimized_build.py
mcp_framework/client/__init__.py
mcp_framework/client/base.py
mcp_framework/client/config.py
mcp_framework/client/enhanced.py
mcp_framework/client/simple.py
mcp_framework/client/tools.py
mcp_framework/core/__init__.py
mcp_framework/core/base.py
mcp_framework/core/config.py
mcp_framework/core/decorators.py
mcp_framework/core/launcher.py
mcp_framework/core/multi_launcher.py
mcp_framework/core/simple_launcher.py
mcp_framework/core/streaming.py
mcp_framework/core/transport.py
mcp_framework/core/utils.py
mcp_framework/server/__init__.py
mcp_framework/server/handlers.py
mcp_framework/server/http_server.py
mcp_framework/server/middleware.py
mcp_framework/server/stdio_server.py
mcp_framework/web/__init__.py
mcp_framework/web/alias_page.py
mcp_framework/web/config_page.py
mcp_framework/web/setup_page.py
mcp_framework/web/test_page.py
mcp_framework/web/templates/test_page.html
mcp_framework-0.1.51.dist-info/licenses/LICENSE
mcp_framework-0.1.51.dist-info/METADATA
mcp_framework-0.1.51.dist-info/WHEEL
mcp_framework-0.1.51.dist-info/entry_points.txt
mcp_framework-0.1.51.dist-info/top_level.txt
mcp_framework-0.1.51.dist-info/RECORD
